INSTALL
LICENSE
MANIFEST.in
README.md
setup.py
GraTeLPy.egg-info/PKG-INFO
GraTeLPy.egg-info/SOURCES.txt
GraTeLPy.egg-info/dependency_links.txt
GraTeLPy.egg-info/requires.txt
GraTeLPy.egg-info/top_level.txt
bin/gratelpy_benchmark
bin/gratelpy_benchmark.spec
bin/gratelpy_check_data
bin/gratelpy_check_data.spec
bin/gratelpy_fragment_server
bin/gratelpy_fragment_server.spec
bin/gratelpy_subclient
bin/gratelpy_subclient.spec
bin/gratelpy_test
bin/gratelpy_test.spec
bin/gratelpy_test_cluster
bin/gratelpy_time
bin/build/gratelpy_test/gratelpy_test
bin/build/gratelpy_test/warngratelpy_test.txt
bin/dist/gratelpy_test/gratelpy_test
doc/Makefile
doc/bibliography.bib
doc/check_data.rst
doc/conf.py
doc/documentation.rst
doc/drawing.rst
doc/examples.rst
doc/fragments.rst
doc/gensg.rst
doc/graph.rst
doc/implementation.rst
doc/index.rst
doc/introduction.rst
doc/lpa.rst
doc/mathematical_background.rst
doc/parse_mechanism.rst
doc/stoich.rst
doc/subclient.rst
doc/subgraphs.rst
gratelpy/__init__.py
gratelpy/counter_python26.py
gratelpy/decorators.py
gratelpy/drawing.py
gratelpy/fragments.py
gratelpy/gensg.py
gratelpy/graph.py
gratelpy/linalg.py
gratelpy/parse_mechanism.py
gratelpy/pyin.py
gratelpy/stoich.py
gratelpy/subgraphs.py
gratelpy/utils.py
gratelpy/mechanisms/__init__.py
gratelpy/mechanisms/cdc42_yeast.txt
gratelpy/mechanisms/double_layer_mapk_mechanism.txt
gratelpy/mechanisms/glycolysis_mechanism.txt
gratelpy/mechanisms/reversible_substrate_inhibition.txt
gratelpy/mechanisms/single_layer_mapk_mechanism.txt
gratelpy/mechanisms/two_layer_cascade_mapk.txt
gratelpy/tests/__init__.py
gratelpy/tests/test_critical_fragments.py
gratelpy/tests/test_fragment_server.py
gratelpy/tests/test_reversible_substrate_inhibition.dat
gratelpy/tests/test_reversible_substrate_inhibition.py
gratelpy/tests/test_stoich_ranks.py